dragonTools/__init__.py
dragonTools/pdf_get_image.py
dragonTools/pdf_to_image.py
dragon_Tools-0.1.2.dist-info/METADATA
dragon_Tools-0.1.2.dist-info/WHEEL
dragon_Tools-0.1.2.dist-info/top_level.txt
dragon_Tools-0.1.2.dist-info/RECORD
